mva_pipeline/__init__.py
mva_pipeline/builder.py
mva_pipeline/cli.py
mva_pipeline/config.yaml
mva_pipeline/llm_filter.py
mva_pipeline/redis_manager.py
mva_pipeline/synth.py
mva_pipeline/tools.py
mva_pipeline/analysis/__init__.py
mva_pipeline/analysis/anomaly.py
mva_pipeline/analysis/pca_yield.py
mva_pipeline/analysis/root_cause.py
mva_pipeline/analysis/unified_importance.py
mva_pipeline/db/__init__.py
mva_pipeline/db/connector.py
mva_pipeline/db/extractor.py
mva_pipeline/db/introspect.py
mva_pipeline/db/kubectl_connector.py
litewaveai_ml_models_yield_data_analysis-0.0.2.dist-info/METADATA
litewaveai_ml_models_yield_data_analysis-0.0.2.dist-info/WHEEL
litewaveai_ml_models_yield_data_analysis-0.0.2.dist-info/entry_points.txt
litewaveai_ml_models_yield_data_analysis-0.0.2.dist-info/top_level.txt
litewaveai_ml_models_yield_data_analysis-0.0.2.dist-info/RECORD
