Metadata-Version: 2.4
Name: LitewaveAI-ml-models-yield-data-analysis
Version: 0.0.2
Summary: Multivariate analytics pipeline for pharmaceutical manufacturing yield optimization
Home-page: https://github.com/aiorch/litewave-ml-models/tree/main/yield_data_analysis
Author: LitewaveAI
Author-email: LitewaveAI <yash@litewave.ai>
Maintainer-email: LitewaveAI <yash@litewave.ai>
License: MIT
Project-URL: Homepage, https://github.com/aiorch/litewave-ml-models/tree/main/yield_data_analysis
Project-URL: Documentation, https://github.com/aiorch/litewave-ml-models/blob/main/yield_data_analysis/README.md
Project-URL: Repository, https://github.com/aiorch/litewave-ml-models/tree/main/yield_data_analysis
Project-URL: Bug Tracker, https://github.com/aiorch/litewave-ml-models/tree/main/yield_data_analysis/issues
Keywords: manufacturing,analytics,pca,shap,anomaly-detection,yield-optimization,pharmaceutical
Classifier: Development Status :: 4 - Beta
Classifier: Intended Audience :: Science/Research
Classifier: Intended Audience :: Manufacturing
Classifier: Topic :: Scientific/Engineering :: Artificial Intelligence
Classifier: Topic :: Scientific/Engineering :: Chemistry
Classifier: License :: OSI Approved :: MIT License
Classifier: Programming Language :: Python :: 3
Classifier: Programming Language :: Python :: 3.8
Classifier: Programming Language :: Python :: 3.9
Classifier: Programming Language :: Python :: 3.10
Classifier: Programming Language :: Python :: 3.11
Classifier: Programming Language :: Python :: 3.12
Requires-Python: >=3.8
Requires-Dist: pandas>=1.3.0
Requires-Dist: numpy>=1.21.0
Requires-Dist: scikit-learn>=1.0.0
Requires-Dist: matplotlib>=3.3.0
Requires-Dist: seaborn>=0.11.0
Requires-Dist: lightgbm>=3.2.0
Requires-Dist: shap>=0.40.0
Requires-Dist: pyod>=1.0.0
Requires-Dist: sqlalchemy>=1.4.0
Requires-Dist: psycopg2-binary>=2.8.0
Requires-Dist: pyyaml>=5.4.0
Requires-Dist: joblib>=1.0.0
Requires-Dist: tqdm>=4.60.0
Requires-Dist: python-dotenv>=0.19.0
Provides-Extra: dev
Requires-Dist: pytest>=6.0; extra == "dev"
Requires-Dist: pytest-cov; extra == "dev"
Requires-Dist: black; extra == "dev"
Requires-Dist: flake8; extra == "dev"
Requires-Dist: mypy; extra == "dev"
Requires-Dist: isort; extra == "dev"
Provides-Extra: docs
Requires-Dist: sphinx; extra == "docs"
Requires-Dist: sphinx-rtd-theme; extra == "docs"
Provides-Extra: llm
Requires-Dist: openai>=1.3; extra == "llm"
Requires-Dist: langchain-core>=0.1; extra == "llm"
Requires-Dist: langchain-openai>=0.1; extra == "llm"
Dynamic: author
Dynamic: home-page
Dynamic: requires-python
